gymprecice/__init__.py
gymprecice/core.py
gymprecice/version.py
gymprecice/utils/__init__.py
gymprecice/utils/constants.py
gymprecice/utils/fileutils.py
gymprecice/utils/multienvutils.py
gymprecice/utils/openfoamutils.py
gymprecice/utils/xmlutils.py
gymprecice-0.1.0.dist-info/LICENSE
gymprecice-0.1.0.dist-info/METADATA
gymprecice-0.1.0.dist-info/WHEEL
gymprecice-0.1.0.dist-info/top_level.txt
gymprecice-0.1.0.dist-info/RECORD
