Metadata-Version: 2.1
Name: gymprecice
Version: 0.1.0
Summary: A framework to designe Reinforcement Learning (RL) environments for Active Flow Control (AFC), as well as a  playground to train Deep Reinforcement Learning (DRL) algorithms for AFC applications.
Home-page: https://github.com/gymprecice/gymprecice/
Author: Mosayeb Shams (lead-developer), Ahmed. H. Elsheikh (supervisor)
Author-email: "Mosayeb Shams (lead developer)" <m.shams@hw.ac.uk>, "Ahmed H. Elsheikh (supervisor)" <a.elsheikh@hw.ac.uk>
License: MIT License
Project-URL: Homepage, https://github.com/gymprecice
Project-URL: Repository, https://github.com/gymprecice/gymprecice
Project-URL: Bug Report, https://github.com/gymprecice/gymprecice/issues
Keywords: Reinforcement Learning,RL,Deep Reinforcement Learning,DRL,AI,Gymnasium,OpenAI Gym,preCICE,Active Flow Control
Classifier: Development Status :: 4 - Beta
Classifier: License :: OSI Approved :: MIT License
Classifier: Intended Audience :: Science/Research
Classifier: Programming Language :: Python :: 3
Classifier: Programming Language :: Python :: 3.7
Classifier: Programming Language :: Python :: 3.8
Classifier: Programming Language :: Python :: 3.9
Classifier: Programming Language :: Python :: 3.10
Classifier: Topic :: Scientific/Engineering :: Artificial Intelligence
Requires-Python: >=3.7
License-File: LICENSE
Requires-Dist: gymnasium (==0.28.0)
Requires-Dist: pyprecice (==2.5.0.1)
Requires-Dist: xmltodict (>=0.13.0)
Requires-Dist: psutil (>=5.9.2)
Provides-Extra: all
Requires-Dist: gymnasium (==0.28.0) ; extra == 'all'
Requires-Dist: pyprecice (==2.5.0.1) ; extra == 'all'
Requires-Dist: xmltodict (>=0.13.0) ; extra == 'all'
Requires-Dist: psutil (>=5.9.2) ; extra == 'all'
Requires-Dist: pytest (==7.1.3) ; extra == 'all'
Requires-Dist: pytest-mock (==3.10.0) ; extra == 'all'
Requires-Dist: matplotlib (>=3.0.0) ; extra == 'all'
Requires-Dist: torch (==1.13.1) ; extra == 'all'
Requires-Dist: scipy (>=1.7.3) ; extra == 'all'
Requires-Dist: black (==23.3.0) ; extra == 'all'
Requires-Dist: pre-commit (==3.2.2) ; extra == 'all'
Requires-Dist: flake8 (==4.0.1) ; extra == 'all'
Requires-Dist: pyright (==1.1.304) ; extra == 'all'
Provides-Extra: dev
Requires-Dist: torch (==1.13.1) ; extra == 'dev'
Requires-Dist: pytest (==7.1.3) ; extra == 'dev'
Requires-Dist: pytest-mock (==3.10.0) ; extra == 'dev'
Requires-Dist: black (==23.3.0) ; extra == 'dev'
Requires-Dist: pre-commit (==3.2.2) ; extra == 'dev'
Requires-Dist: flake8 (==4.0.1) ; extra == 'dev'
Requires-Dist: pyright (==1.1.304) ; extra == 'dev'
Requires-Dist: matplotlib (>=3.0.0) ; extra == 'dev'
Requires-Dist: scipy (>=1.7.3) ; extra == 'dev'
Provides-Extra: test
Requires-Dist: pytest (==7.1.3) ; extra == 'test'
Requires-Dist: pytest-mock (==3.10.0) ; extra == 'test'
Provides-Extra: tutorial
Requires-Dist: torch (==1.13.1) ; extra == 'tutorial'
Requires-Dist: matplotlib (>=3.0.0) ; extra == 'tutorial'
Requires-Dist: scipy (>=1.7.3) ; extra == 'tutorial'
